tasks_logger/__init__.py
tasks_logger/main.py
tasks_logger-0.1.0.dist-info/METADATA
tasks_logger-0.1.0.dist-info/WHEEL
tasks_logger-0.1.0.dist-info/top_level.txt
tasks_logger-0.1.0.dist-info/RECORD
