Metadata-Version: 2.1
Name: tasks-logger
Version: 0.1.0
Summary: Simplify complex logging in Python with customizable, color-coded, and thread-safe outputs.
Home-page: https://github.com/glizzykingdreko/tasks-logger
Author: GlizzyKingDreko
Author-email: glizzykingdreko@protonmail.com
Classifier: Development Status :: 3 - Alpha
Classifier: Intended Audience :: Developers
Classifier: Topic :: Software Development :: Libraries :: Python Modules
Classifier: License :: OSI Approved :: MIT License
Classifier: Programming Language :: Python :: 3
Classifier: Programming Language :: Python :: 3.6
Classifier: Programming Language :: Python :: 3.7
Classifier: Programming Language :: Python :: 3.8
Classifier: Programming Language :: Python :: 3.9
Classifier: Programming Language :: Python :: 3.10
Classifier: Operating System :: OS Independent
Requires-Python: >=3.6
Requires-Dist: colorama
